sd_clients/__init__.py
sd_clients/api_gateway_client.py
sd_clients/client_store.py
sd_clients/service_directory_client.py
sd_clients/settings.py
sd_clients-3.0.0.dist-info/LICENSE.txt
sd_clients-3.0.0.dist-info/METADATA
sd_clients-3.0.0.dist-info/WHEEL
sd_clients-3.0.0.dist-info/top_level.txt
sd_clients-3.0.0.dist-info/RECORD
