Metadata-Version: 2.1
Name: sd_clients
Version: 3.0.0
Summary: Clients for communication with e360 Service Directory and Api Gateway
Author: IQVIA
Author-email: e360pypi@iqvia.com
License: Apache License 2.0
Classifier: Environment :: Web Environment
Classifier: Intended Audience :: Developers
Classifier: License :: OSI Approved :: Apache Software License
Classifier: Operating System :: OS Independent
Classifier: Programming Language :: Python
Classifier: Programming Language :: Python :: 3.9
Classifier: Programming Language :: Python :: 3.10
Classifier: Programming Language :: Python :: 3.11
Classifier: Topic :: Internet :: WWW/HTTP
Classifier: Topic :: Internet :: WWW/HTTP :: Dynamic Content
Requires-Python: >=3.9
License-File: LICENSE.txt
Requires-Dist: clients-core <4,>=3
